admin_api/__init__.py
admin_api/auth.py
admin_api/core.py
admin_api/decorators.py
admin_api/exceptions.py
admin_api/fields.py
admin_api/log.py
admin_api/pagination.py
admin_api/sites.py
admin_api/viewsets.py
django_admin_api-0.0.8.dist-info/METADATA
django_admin_api-0.0.8.dist-info/WHEEL
django_admin_api-0.0.8.dist-info/top_level.txt
django_admin_api-0.0.8.dist-info/RECORD
